gooey_quick/__init__.py
gooey_quick/__main__.py
gooey_quick/converters.py
gooey_quick/introspection.py
gooey_quick/types.py
gooey_quick-1.0.1.dist-info/LICENSE.txt
gooey_quick-1.0.1.dist-info/METADATA
gooey_quick-1.0.1.dist-info/WHEEL
gooey_quick-1.0.1.dist-info/top_level.txt
gooey_quick-1.0.1.dist-info/RECORD
