Metadata-Version: 2.1
Name: gooey-quick
Version: 1.0.1
Summary: Turn type-hinted Python program into a GUI application with few additional lines of code
Home-page: https://github.com/jacadzaca/gooey_quick
Author: jacadzaca
Author-email: vitouejj@gmail.com
License: MIT
License-File: LICENSE.txt
Requires-Dist: Gooey
